create_lilypad_module/__init__.py
create_lilypad_module/scaffold.py
create_lilypad_module/templates/.dockerignore
create_lilypad_module/templates/.env
create_lilypad_module/templates/.gitignore
create_lilypad_module/templates/Dockerfile
create_lilypad_module/templates/README.md
create_lilypad_module/templates/lilypad_module.json.tmpl
create_lilypad_module/templates/requirements.txt
create_lilypad_module/templates/config/constants.py
create_lilypad_module/templates/scripts/docker_build.py
create_lilypad_module/templates/scripts/download_models.py
create_lilypad_module/templates/scripts/run_module.py
create_lilypad_module/templates/src/run_inference.py
create_lilypad_module-0.1.49.dist-info/METADATA
create_lilypad_module-0.1.49.dist-info/WHEEL
create_lilypad_module-0.1.49.dist-info/entry_points.txt
create_lilypad_module-0.1.49.dist-info/top_level.txt
create_lilypad_module-0.1.49.dist-info/RECORD
